<?xml version="1.0"?>
<Form Name="{WorkflowName}{FormName}Form" Width="1000" Height="600" BackColor="ThemeBackgroundColor" StartPosition="CenterScreen" FontStyle="ThemeFontStyle" ForeColor="ThemeForeColor" ValidationType="Flat" FlatColor="ThemeFlatColor" FlatWidth="2" StatusBar="True" MaximizeBox="True" FormBorderStyle="Sizable">
  <Parameters>
    <Parameter Name="Title">{FormTitle}</Parameter>
  </Parameters>
  
  <Appearance>
    <Colors>
      <Color Name="ThemeForeColor" Red="0" Green="0" Blue="0" Alpha="255" />
      <Color Name="ThemeBackgroundColor" Red="255" Green="255" Blue="255" Alpha="255" />
      <Color Name="ThemeFlatColor" Red="255" Green="0" Blue="0" Alpha="255" />
      <Color Name="ThemeSeparateBackgroundColor" Red="225" Green="225" Blue="225" Alpha="255" />

      <Color Name="HeadBackgroundColor" Red="221" Green="232" Blue="246" Alpha="255" />
      <Color Name="HeadForeColor" Red="70" Green="70" Blue="70" Alpha="255" />
	  
      <Color Name="LabelForeColor" Red="100" Green="100" Blue="100" Alpha="255" />
      <Color Name="TableBackgroundColor" Red="200" Green="200" Blue="200" Alpha="255" />
      <Color Name="TableArchiveColor" Red="230" Green="230" Blue="230" Alpha="255" />
	  
      <!-- Стили кнопок -->
      <Color Name="ButtonFlatBorderColor" Red="225" Green="225" Blue="225" Alpha="255" />
      <Color Name="ButtonFlatMouseDownBackColor" Red="201" Green="219" Blue="241" Alpha="255" />
      <Color Name="ButtonFlatMouseOverBackColor" Red="228" Green="237" Blue="248" Alpha="255" />
    </Colors>

    <FontStyles>
      <FontStyle Name="ThemeFontStyle" Font="Segoe UI" Size="9" />
      <FontStyle Name="HeadFontStyle" Font="Segoe UI" Size="15" />
      <FontStyle Name="LabelFontStyle" Font="Segoe UI" Size="9" Italic="True" />
      <FontStyle Name="ButtonFontStyle" Font="Segoe UI" Size="10" />
    </FontStyles>
  </Appearance>

  <DataConnections> </DataConnections>

  <Conditions>
    <Condition Name="FormClosingCondition" Type="FormClosingCondition" Assembly="Conditions" />
  </Conditions>

  <Commands>
    <Command Name="FormCloseCommand" Type="FormCloseCommand" Assembly="Commands" />
  </Commands>

  <Executions>
    <Execution>
      <ConditionExpression>
        <Condition Name="FormClosingCondition" />
      </ConditionExpression>
      <Commands>
        <Command Name="FormCloseCommand" />
      </Commands>
    </Execution>
  </Executions>

  <MyObjects>
    <MyObject Name="HeadPanel" Type="Panel" Assembly="BaseControls">
      <Top>0</Top>
      <Left>0</Left>
      <Height>50</Height>
      <Width>
        <Form>
          <Property Name="Width" />
        </Form>
      </Width>
      <BackColor>HeadBackgroundColor</BackColor>

      <MyObject Name="HeadLabel" Type="Label" Assembly="BaseControls" ChangeForm="False">
        <Top>0</Top>
        <Left>10</Left>
        <Height>
          <Object Name="HeadPanel">
            <Property Name="Height" />
          </Object>
        </Height>
        <Width>
          <Calculate>
            <Expression>\{0} - \{1} - 10</Expression>
            <Items>
              <Item>
                <Object Name="HeadPanel">
                  <Property Name="Width" />
                </Object>
              </Item>
              <Item>
                <Object Name="HeadLabel">
                  <Property Name="Left" />
                </Object>
              </Item>
            </Items>
          </Calculate>
        </Width>
        <FontStyle>HeadFontStyle</FontStyle>
        <ForeColor>HeadForeColor</ForeColor>
        <TextAlign>MiddleLeft</TextAlign>
        <Text>
          <Parameter Name="Title" />
        </Text>
      </MyObject>
    </MyObject>

    <MyObject Name="ContentPanel" Type="Panel" Assembly="BaseControls">
      <Top>
        <Object Name="HeadPanel">
          <Property Name="Bottom" />
        </Object>
      </Top>
      <Left>0</Left>
      <Height>
        <Calculate>
          <Expression>\{0} - \{1}</Expression>
          <Items>
            <Item>
              <Form>
                <Property Name="Height" />
              </Form>
            </Item>
            <Item>
              <Object Name="ContentPanel">
                <Property Name="Top" />
              </Object>
            </Item>
          </Items>
        </Calculate>
      </Height>
      <Width>
        <Form>
          <Property Name="Width" />
        </Form>
      </Width>
      <TabIndex>1</TabIndex>
      <BackColor>ThemeBackgroundColor</BackColor>
	  
	  <!-- Insert your content-->
	  
    </MyObject>
  </MyObjects>
</Form>