<?xml version="1.0"?>
<Form Name="TemplateStartForm" Width="900" Height="400" BackColor="ThemeBackgroundColor" StartPosition="CenterScreen" FontStyle="ThemeFontStyle" ForeColor="ThemeForeColor" ValidationType="Flat" FlatColor="ThemeFlatColor" FlatWidth="2" StatusBar="True" MaximizeBox="True" FormBorderStyle="Sizable" Opacity="0">
  <Parameters>
    <Parameter Name="Title">Заказы</Parameter>
  </Parameters>

  <Appearance>
    <Colors>
      <Color Name="ThemeForeColor" Red="0" Green="0" Blue="0" Alpha="255" />
      <Color Name="ThemeBackgroundColor" Red="255" Green="255" Blue="255" Alpha="255" />
      <Color Name="ThemeFlatColor" Red="255" Green="0" Blue="0" Alpha="255" />
      <Color Name="ThemeSeparateBackgroundColor" Red="225" Green="225" Blue="225" Alpha="255" />

      <Color Name="HeadBackgroundColor" Red="221" Green="232" Blue="246" Alpha="255" />
      <Color Name="HeadForeColor" Red="70" Green="70" Blue="70" Alpha="255" />

      <Color Name="LabelForeColor" Red="100" Green="100" Blue="100" Alpha="255" />
      <Color Name="TableBackgroundColor" Red="200" Green="200" Blue="200" Alpha="255" />
      <Color Name="TableArchiveColor" Red="230" Green="230" Blue="230" Alpha="255" />

      <!-- Стили кнопок -->
      <Color Name="ButtonFlatBorderColor" Red="225" Green="225" Blue="225" Alpha="255" />
      <Color Name="ButtonFlatMouseDownBackColor" Red="201" Green="219" Blue="241" Alpha="255" />
      <Color Name="ButtonFlatMouseOverBackColor" Red="228" Green="237" Blue="248" Alpha="255" />

      <!-- Стили фильтров -->
      <Color Name="ActiveFilterColor" Red="228" Green="237" Blue="248" Alpha="255" />
      <Color Name="InactiveFilterColor" Red="255" Green="255" Blue="255" Alpha="255" />
    </Colors>

    <FontStyles>
      <FontStyle Name="ThemeFontStyle" Font="Segoe UI" Size="9" />
      <FontStyle Name="HeadFontStyle" Font="Segoe UI" Size="15" />
      <FontStyle Name="LabelFontStyle" Font="Segoe UI" Size="9" Italic="True" />
      <FontStyle Name="ButtonFontStyle" Font="Segoe UI" Size="10" />
    </FontStyles>
  </Appearance>

  <DataConnections>
    <DataConnection Name="OrderPrimaryGetDataConnection" Type="PrimaryGetDataConnection" Assembly="DataConnections">
      <ManualLoad>True</ManualLoad>
      <SqlQuery Name="OrderSelectSqlQuery" Type="Select">
        <Workflow Name="Template" />
        <Fields>
          <Field Name="OrderId" />
          <Field Name="ClientId" />
          <Field Name="CityId" />
          <Field Name="OrderNumber" />
          <Field Name="OrderDate" />
          <Field Name="Count" />
        </Fields>
        <Parameters>
          <Parameter NativeName="Filter" RefreshQuery="False">
            <Value>
              <Object Name="ActiveFilterVariable" />
            </Value>
          </Parameter>
          <Parameter NativeName="StartDate" RefreshQuery="False">
            <Value>
              <Object Name="StartDateDateTimePicker" />
            </Value>
          </Parameter>
          <Parameter NativeName="EndDate" RefreshQuery="False">
            <Value>
              <Object Name="EndDateDateTimePicker" />
            </Value>
          </Parameter>
          <Parameter NativeName="Limit">
            <Value>
              <Object Name="ItemsPerPageComboBox" />
            </Value>
          </Parameter>
          <Parameter NativeName="Page">
            <Value>
              <Object Name="CurrentPageVariable" />
            </Value>
          </Parameter>
        </Parameters>
      </SqlQuery>
    </DataConnection>

    <DataConnection Name="ClientPrimaryGetDataConnection" Type="PrimaryGetDataConnection" Assembly="DataConnections">
      <ManualLoad>True</ManualLoad>
      <SqlQuery Name="ClientSimpleSelectSqlQuery" Type="Select">
        <Workflow Name="Template" />
        <Fields>
          <Field Name="ClientId" />
          <Field Name="Title" />
        </Fields>
      </SqlQuery>
    </DataConnection>

    <DataConnection Name="CityPrimaryGetDataConnection" Type="PrimaryGetDataConnection" Assembly="DataConnections">
      <ManualLoad>True</ManualLoad>
      <SqlQuery Name="CitySimpleSelectSqlQuery" Type="Select">
        <Workflow Name="Template" />
        <Fields>
          <Field Name="CityId" />
          <Field Name="Title" />
        </Fields>
      </SqlQuery>
    </DataConnection>

    <DataConnection Name="OrderDeleteSetDataConnection" Type="SetDataConnection" Assembly="DataConnections">
      <Workflow Name="Template" />
      <SqlQueries>
        <SqlQuery Name="OrderDeleteSqlQuery" Type="Delete" />
      </SqlQueries>
      <Parameters>
        <Parameter NativeName="OrderId">
          <Value>
            <Object Name="OrderDatabaseTable">
              <Property Name="SelectedRowCellValueByColumnName">
                <Parameters>
                  <Parameter Name="ColumnName">OrderId</Parameter>
                </Parameters>
              </Property>
            </Object>
          </Value>
        </Parameter>
      </Parameters>
    </DataConnection>

    <DataConnection Name="EmptyOrderInsertSetDataConnection" Type="SetDataConnection" Assembly="DataConnections">
      <Workflow Name="Template" />
      <SqlQueries>
        <SqlQuery Name="EmptyOrderInsertSqlQuery" Type="Insert" />
      </SqlQueries>
    </DataConnection>
  </DataConnections>

  <Conditions>
    <Condition Name="FormClosingCondition" Type="FormClosingCondition" Assembly="Conditions" />

    <Condition Name="FormLoadedCondition" Type="FormLoadedCondition" Assembly="Conditions" />

    <Condition Name="OrderSelectedCondition" Type="GreaterCondition" Assembly="Conditions">
      <Items>
        <Item>
          <Object Name="OrderDatabaseTable">
            <Property Name="SelectedRowsCount" />
          </Object>
        </Item>
        <Item>0</Item>
      </Items>
      <DataType Type="IntegerDataType" />
    </Condition>

    <Condition Name="OrderCellDoubleClickCondition" Type="CellDoubleClickCondition" Assembly="Conditions">
      <Table Name="OrderDatabaseTable" />
    </Condition>

    <Condition Name="OrderAddFormUpdatedTrueEqualCondition" Type="EqualCondition" Assembly="Conditions">
      <AlwaysChange Value="True" />
      <Items>
        <Item>
          <Command Name="OrderAddFormShowCommand" Parameter="Updated" />
        </Item>
        <Item>True</Item>
      </Items>
      <DataType Type="BooleanDataType" />
    </Condition>

    <Condition Name="OrderEditFormUpdatedTrueEqualCondition" Type="EqualCondition" Assembly="Conditions">
      <AlwaysChange Value="True" />
      <Items>
        <Item>
          <Command Name="OrderEditFormShowCommand" Parameter="Updated" />
        </Item>
        <Item>True</Item>
      </Items>
      <DataType Type="BooleanDataType" />
    </Condition>

    <Condition Name="FilterTodayIsActiveEqualCondition" Type="EqualCondition" Assembly="Conditions">
      <Items>
        <Item>
          <Object Name="ActiveFilterVariable" />
        </Item>
        <Item>Today</Item>
      </Items>
    </Condition>

    <Condition Name="FilterCurrentWeekIsActiveEqualCondition" Type="EqualCondition" Assembly="Conditions">
      <Items>
        <Item>
          <Object Name="ActiveFilterVariable" />
        </Item>
        <Item>CurrentWeek</Item>
      </Items>
    </Condition>

    <Condition Name="FilterFortnightIsActiveEqualCondition" Type="EqualCondition" Assembly="Conditions">
      <Items>
        <Item>
          <Object Name="ActiveFilterVariable" />
        </Item>
        <Item>Fortnight</Item>
      </Items>
    </Condition>

    <Condition Name="FilterPeriodIsActiveEqualCondition" Type="EqualCondition" Assembly="Conditions">
      <Items>
        <Item>
          <Object Name="ActiveFilterVariable" />
        </Item>
        <Item>Period</Item>
      </Items>
    </Condition>


    <!-- Pagination -->
    <!-- Pagination -->
    <!-- Pagination -->
    <Condition Name="NumberOfOrdersEqual0Condition" Type="EqualCondition" Assembly="Conditions">
      <Items>
        <Item>
          <DataConnection SourceDataConnection="OrderPrimaryGetDataConnection">
            <Property Name="Count" />
          </DataConnection>
        </Item>
        <Item>0</Item>
      </Items>
      <DataType Type="IntegerDataType" />
    </Condition>

    <Condition Name="NumberOfOrdersVariableEqual0Condition" Type="EqualCondition" Assembly="Conditions">
      <Items>
        <Item>
          <Object Name="NumberOfOrdersVariable" />
        </Item>
        <Item>0</Item>
      </Items>
      <DataType Type="IntegerDataType" />
    </Condition>

    <Condition Name="ItemsPerPageComboBoxIsNullCondition" Type="IsNullCondition" Assembly="Conditions">
      <Items>
        <Item>
          <Object Name="ItemsPerPageComboBox" />
        </Item>
      </Items>
    </Condition>

    <Condition Name="CurrentPageVariableEqual1Condition" Type="EqualCondition" Assembly="Conditions">
      <Items>
        <Item>
          <Object Name="CurrentPageVariable" />
        </Item>
        <Item>1</Item>
      </Items>
      <DataType Type="IntegerDataType" />
    </Condition>

    <Condition Name="CurrentPageVariableEqualMaxCondition" Type="EqualCondition" Assembly="Conditions">
      <Items>
        <Item>
          <Object Name="CurrentPageVariable" />
        </Item>
        <Item>
          <Object Name="TotalPagesVariable" />
        </Item>
      </Items>
      <DataType Type="IntegerDataType" />
    </Condition>

    <Condition Name="CurrentPageTextBoxKeyEnterPressCondition" Type="KeyDownCondition" Assembly="Conditions">
      <Object Name="CurrentPageTextBox" />
      <Key Value="Enter" />
    </Condition>

    <Condition Name="CurrentPageTextBoxNotLessMinCondition" Type="NotLessCondition" Assembly="Conditions">
      <Items>
        <Item>
          <Object Name="CurrentPageTextBox" />
        </Item>
        <Item>1</Item>
      </Items>
      <DataType Type="IntegerDataType" />
    </Condition>

    <Condition Name="CurrentPageTextBoxNotGreaterMaxCondition" Type="NotGreaterCondition" Assembly="Conditions">
      <Items>
        <Item>
          <Object Name="CurrentPageTextBox" />
        </Item>
        <Item>
          <Object Name="TotalPagesVariable" />
        </Item>
      </Items>
      <DataType Type="IntegerDataType" />
    </Condition>

    <!--STOP PAGINATION-->
    <!--STOP PAGINATION-->
    <!--STOP PAGINATION-->
  </Conditions>

  <Commands>
    <Command Name="FormCloseCommand" Type="FormCloseCommand" Assembly="Commands" />

    <Command Name="FormShowValueSetCommand" Type="ValueSetCommand" Assembly="Commands">
      <Form>
        <Property Name="Opacity">1</Property>
      </Form>
    </Command>

    <Command Name="OrderDataConnectionRefreshCommand" Type="DataConnectionRefreshCommand" Assembly="Commands">
      <DataConnections>
        <DataConnection Name="OrderPrimaryGetDataConnection" />
      </DataConnections>
    </Command>

    <Command Name="CityListFormShowCommand" Type="FormShowCommand" Assembly="Commands">
      <Xml Type="Path">TemplateCityList.xml</Xml>
      <Show Type="None" />
    </Command>

    <Command Name="ClientListFormShowCommand" Type="FormShowCommand" Assembly="Commands">
      <Xml Type="Path">TemplateClientList.xml</Xml>
      <Show Type="None" />
    </Command>

    <Command Name="OperationListFormShowCommand" Type="FormShowCommand" Assembly="Commands">
      <Xml Type="Path">TemplateOperationList.xml</Xml>
      <Show Type="None" />
    </Command>

    <Command Name="UnitListFormShowCommand" Type="FormShowCommand" Assembly="Commands">
      <Xml Type="Path">TemplateUnitList.xml</Xml>
      <Show Type="None" />
    </Command>

    <Command Name="MaterialListFormShowCommand" Type="FormShowCommand" Assembly="Commands">
      <Xml Type="Path">TemplateMaterialList.xml</Xml>
      <Show Type="None" />
    </Command>

    <Command Name="CashListFormShowCommand" Type="FormShowCommand" Assembly="Commands">
      <Xml Type="Path">TemplateCashList.xml</Xml>
      <Show Type="None" />
    </Command>

    <Command Name="OrderAddFormShowCommand" Type="FormShowCommand" Assembly="Commands">
      <Xml Type="Path">TemplateOrderEdit.xml</Xml>
      <Show Type="None" />
      <Parameters>
        <Parameter Name="OrderId">
          <Command Name="EmptyOrderInsertSaveCommand" />
        </Parameter>
      </Parameters>
    </Command>

    <Command Name="OrderEditFormShowCommand" Type="FormShowCommand" Assembly="Commands">
      <Xml Type="Path">TemplateOrderEdit.xml</Xml>
      <Show Type="None" />
      <Parameters>
        <Parameter Name="Edit">True</Parameter>
        <Parameter Name="OrderId">
          <Object Name="OrderDatabaseTable">
            <Property Name="SelectedRowCellValueByColumnName">
              <Parameters>
                <Parameter Name="ColumnName">OrderId</Parameter>
              </Parameters>
            </Property>
          </Object>
        </Parameter>
      </Parameters>
    </Command>

    <Command Name="AccountListFormShowCommand" Type="FormShowCommand" Assembly="Commands">
      <Xml Type="Path">TemplateAccountList.xml</Xml>
      <Show Type="None" />
    </Command>

    <Command Name="OrderDeleteSaveCommand" Type="SaveCommand" Assembly="Commands">
      <DataConnections>
        <DataConnection Name="OrderDeleteSetDataConnection" />
      </DataConnections>
    </Command>

    <Command Name="OrderDeleteMessageBoxCommand" Type="MessageBoxCommand" Assembly="Commands">
      <Caption>Удаление</Caption>
      <Text>Вы действительно хотите удалить выбранную запись?</Text>
      <Buttons Type="YesNo" />
      <Icon Type="Question" />
    </Command>

    <Command Name="OrderSelectInTableValueSetCommand" Type="ValueSetCommand" Assembly="Commands">
      <Object Name="OrderDatabaseTable">
        <Property Name="SelectRowByFieldValue">
          <Parameters>
            <Parameter Name="ColumnName">OrderId</Parameter>
            <Parameter Name="Value">
              <Input />
            </Parameter>
          </Parameters>
        </Property>
      </Object>
    </Command>

    <Command Name="CityDataConnectionRefreshCommand" Type="DataConnectionRefreshCommand" Assembly="Commands">
      <DataConnections>
        <DataConnection Name="CityPrimaryGetDataConnection" Packet="True" />
      </DataConnections>
    </Command>

    <Command Name="ClientDataConnectionRefreshCommand" Type="DataConnectionRefreshCommand" Assembly="Commands">
      <DataConnections>
        <DataConnection Name="ClientPrimaryGetDataConnection" Packet="True" />
      </DataConnections>
    </Command>

    <Command Name="AllPrimaryDataConnectionRefreshCommand" Type="DataConnectionRefreshCommand" Assembly="Commands">
      <Parallel>True</Parallel>
      <DataConnections>
        <DataConnection Name="CityPrimaryGetDataConnection" Packet="True" />
        <DataConnection Name="ClientPrimaryGetDataConnection" Packet="True" />
      </DataConnections>
    </Command>

    <Command Name="ActiveFilterValueSetCommand" Type="ValueSetCommand" Assembly="Commands">
      <Object Name="ActiveFilterVariable">
        <Input />
      </Object>
    </Command>

    <Command Name="DeletedOrderListFormShowCommand" Type="FormShowCommand" Assembly="Commands">
      <Xml Type="Path">TemplateDeletedOrderList.xml</Xml>
      <Show Type="None" />
    </Command>

    <Command Name="BudgetReportFormShowCommand" Type="FormShowCommand" Assembly="Commands">
      <Xml Type="Path">TemplateReportBudget.xml</Xml>
      <Show Type="None" />
    </Command>

    <Command Name="EmptyOrderInsertSaveCommand" Type="SaveCommand" Assembly="Commands">
      <DataConnections>
        <DataConnection Name="EmptyOrderInsertSetDataConnection" />
      </DataConnections>
    </Command>

    <Command Name="SettingsFormShowCommand" Type="FormShowCommand" Assembly="Commands">
      <Xml Type="Path">TemplateSettings.xml</Xml>
      <Show Type="None" />
    </Command>

    <Command Name="UserListFormShowCommand" Type="FormShowCommand" Assembly="Commands">
      <Xml Type="Path">TemplateUserList.xml</Xml>
      <Show Type="None" />
    </Command>

    <Command Name="LoginFormShowCommand" Type="FormShowCommand" Assembly="Commands">
      <Xml Type="Path">TemplateLogin.xml</Xml>
      <Show Type="Modal" />
    </Command>

    <Command Name="ReloginFormShowCommand" Type="FormShowCommand" Assembly="Commands">
      <Xml Type="Path">TemplateLogin.xml</Xml>
      <Show Type="Modal" />
    </Command>

    <!-- Paggination -->
    <!-- Paggination -->
    <!-- Paggination -->
    <Command Name="CurrentPageVariableValueSetCommand" Type="ValueSetCommand" Assembly="Commands">
      <Object Name="CurrentPageVariable">
        <Input />
      </Object>
    </Command>

    <Command Name="CurrentPageVariableDecValueSetCommand" Type="ValueSetCommand" Assembly="Commands">
      <Object Name="CurrentPageVariable">
        <Formula>
          <Minus DataType="IntegerDataType">
            <Item>
              <Object Name="CurrentPageVariable" />
            </Item>
            <Item>1</Item>
          </Minus>
        </Formula>
      </Object>
    </Command>

    <Command Name="CurrentPageVariableIncValueSetCommand" Type="ValueSetCommand" Assembly="Commands">
      <Object Name="CurrentPageVariable">
        <Formula>
          <Plus DataType="IntegerDataType">
            <Item>
              <Object Name="CurrentPageVariable" />
            </Item>
            <Item>1</Item>
          </Plus>
        </Formula>
      </Object>
    </Command>

  </Commands>

  <Executions>
    <Execution>
      <ConditionExpression>
        <Condition Name="FormLoadedCondition" />
      </ConditionExpression>
      <Commands>
        <Command Name="LoginFormShowCommand" />
      </Commands>
    </Execution>

    <Execution>
      <ConditionExpression>
        <Command Name="LoginFormShowCommand" Parameter="Updated" />
      </ConditionExpression>
      <Commands>
        <Command Name="FormShowValueSetCommand" />
        <Command Name="AllPrimaryDataConnectionRefreshCommand" />
        <Command Name="OrderDataConnectionRefreshCommand" />
      </Commands>
    </Execution>

    <Execution>
      <ConditionExpression>
        <Not>
          <Command Name="LoginFormShowCommand" Parameter="Updated" />
        </Not>
      </ConditionExpression>
      <Commands>
        <Command Name="FormCloseCommand" />
      </Commands>
    </Execution>

    <Execution>
      <ConditionExpression>
        <Command Name="ReloginFormShowCommand" Parameter="Updated" />
      </ConditionExpression>
      <Commands>
        <Command Name="AllPrimaryDataConnectionRefreshCommand" />
        <Command Name="OrderDataConnectionRefreshCommand" />
      </Commands>
    </Execution>

    <Execution>
      <ConditionExpression>
        <Condition Name="FormClosingCondition" />
      </ConditionExpression>
      <Commands>
        <Command Name="FormCloseCommand" />
      </Commands>
    </Execution>

    <Execution>
      <ConditionExpression>
        <Condition Name="OrderAddFormUpdatedTrueEqualCondition" />
      </ConditionExpression>
      <Commands>
        <Command Name="OrderDataConnectionRefreshCommand" />
        <Command Name="OrderSelectInTableValueSetCommand">
          <Command Name="OrderAddFormShowCommand" Parameter="OrderId" />
        </Command>
      </Commands>
    </Execution>

    <Execution>
      <ConditionExpression>
        <Condition Name="OrderEditFormUpdatedTrueEqualCondition" />
      </ConditionExpression>
      <Commands>
        <Command Name="OrderDataConnectionRefreshCommand" />
        <Command Name="OrderSelectInTableValueSetCommand">
          <Command Name="OrderEditFormShowCommand" Parameter="OrderId" />
        </Command>
      </Commands>
    </Execution>

    <Execution>
      <ConditionExpression>
        <Command Name="OrderDeleteMessageBoxCommand" Parameter="Yes" />
      </ConditionExpression>
      <Commands>
        <Command Name="OrderDeleteSaveCommand" />
        <Command Name="OrderDataConnectionRefreshCommand" />
      </Commands>
    </Execution>

    <Execution>
      <ConditionExpression>
        <Condition Name="OrderCellDoubleClickCondition" />
      </ConditionExpression>
      <Commands>
        <Command Name="OrderEditFormShowCommand" />
      </Commands>
    </Execution>

    <Execution>
      <ConditionExpression>
        <Command Name="ClientListFormShowCommand" Parameter="Updated" />
      </ConditionExpression>
      <Commands>
        <Command Name="ClientDataConnectionRefreshCommand" />
      </Commands>
    </Execution>

    <Execution>
      <ConditionExpression>
        <Command Name="CityListFormShowCommand" Parameter="Updated" />
      </ConditionExpression>
      <Commands>
        <Command Name="CityDataConnectionRefreshCommand" />
      </Commands>
    </Execution>

    <Execution>
      <ConditionExpression>
        <Condition Name="CurrentPageTextBoxKeyEnterPressCondition" />
      </ConditionExpression>
      <Commands>
        <If>
          <When>
            <And>
              <Condition Name="CurrentPageTextBoxNotGreaterMaxCondition" />
              <Condition Name="CurrentPageTextBoxNotLessMinCondition" />
            </And>
          </When>
          <Then>
            <Command Name="CurrentPageVariableValueSetCommand">
              <Object Name="CurrentPageTextBox" />
            </Command>
          </Then>
          <ElseIf>
            <When>
              <Not>
                <Condition Name="CurrentPageTextBoxNotLessMinCondition" />
              </Not>
            </When>
            <Then>
              <Command Name="CurrentPageVariableValueSetCommand">1</Command>
            </Then>
          </ElseIf>
          <ElseIf>
            <When>
              <Not>
                <Condition Name="CurrentPageTextBoxNotGreaterMaxCondition" />
              </Not>
            </When>
            <Then>
              <Command Name="CurrentPageVariableValueSetCommand">
                <Object Name="TotalPagesVariable" />
              </Command>
            </Then>
          </ElseIf>
        </If>
      </Commands>
    </Execution>
  </Executions>

  <MainMenu>
    <MenuItem Name="FileMenuItem" Type="MenuItem">
      <Title>Файл</Title>
      <Items>
        <MenuItem Name="ReloginMenuItem" Type="MenuItem">
          <Title>Войти как...</Title>
          <Command Name="ReloginFormShowCommand" />
        </MenuItem>

        <MenuItem Name="ReloginFileRefreshSeparator" Type="Separator" />

        <MenuItem Name="FileRefreshMenuItem" Type="MenuItem">
          <Title>Обновить</Title>
          <Command Name="OrderDataConnectionRefreshCommand" />
        </MenuItem>

        <MenuItem Name="FileSeparator" Type="Separator" />

        <MenuItem Name="FileExitMenuItem" Type="MenuItem">
          <Title>Выход</Title>
          <Command Name="FormCloseCommand" />
        </MenuItem>
      </Items>
    </MenuItem>

    <MenuItem Name="ListMenuItem" Type="MenuItem">
      <Title>Списки</Title>
      <Items>
        <MenuItem Name="CityMenuItem" Type="MenuItem">
          <Title>Города...</Title>
          <Command Name="CityListFormShowCommand" />
        </MenuItem>

        <MenuItem Name="ClientMenuItem" Type="MenuItem">
          <Title>Клиенты...</Title>
          <Command Name="ClientListFormShowCommand" />
        </MenuItem>

        <MenuItem Name="List1Separator" Type="Separator" />

        <MenuItem Name="OperationListMenuItem" Type="MenuItem">
          <Title>Назначения платежей</Title>
          <Command Name="OperationListFormShowCommand" />
        </MenuItem>

        <MenuItem Name="AccountListMenuItem" Type="MenuItem">
          <Title>Счета</Title>
          <Command Name="AccountListFormShowCommand" />
        </MenuItem>

        <MenuItem Name="OperationUnitSeparator" Type="Separator" />

        <MenuItem Name="UnitListMenuItem" Type="MenuItem">
          <Title>Единицы измерения...</Title>
          <Command Name="UnitListFormShowCommand" />
        </MenuItem>

        <MenuItem Name="MaterialListMenuItem" Type="MenuItem">
          <Title>ТМЦ...</Title>
          <Command Name="MaterialListFormShowCommand" />
        </MenuItem>
      </Items>
    </MenuItem>

    <MenuItem Name="FinanceMenuItem" Type="MenuItem">
      <Title>Финансы</Title>
      <Items>
        <MenuItem Name="CashListMenuItem" Type="MenuItem">
          <Title>Касса</Title>
          <Command Name="CashListFormShowCommand" />
        </MenuItem>
      </Items>
    </MenuItem>

    <MenuItem Name="LogMenuItem" Type="MenuItem">
      <Title>Журналы</Title>
      <Items>
        <MenuItem Name="DeletedRentsListMenuItem" Type="MenuItem">
          <Title>Список удаленных заказов...</Title>
          <Command Name="DeletedOrderListFormShowCommand" />
        </MenuItem>
      </Items>
    </MenuItem>

    <MenuItem Name="ReportMenuItem" Type="MenuItem">
      <Title>Отчеты</Title>
      <Items>
        <MenuItem Name="BudgetReportMenuItem" Type="MenuItem">
          <Title>Отчет по бюджету</Title>
          <Command Name="BudgetReportFormShowCommand" />
        </MenuItem>
      </Items>
    </MenuItem>

    <MenuItem Name="AdminMenuItem" Type="MenuItem">
      <Title>Администрирование</Title>
      <Items>
        <MenuItem Name="UserListMenuItem" Type="MenuItem">
          <Title>Пользователи...</Title>
          <Command Name="UserListFormShowCommand" />
        </MenuItem>
        <MenuItem Name="UserSettingsSeparator" Type="Separator" />
        <MenuItem Name="SettingsMenuItem" Type="MenuItem">
          <Title>Настройки...</Title>
          <Command Name="SettingsFormShowCommand" />
        </MenuItem>
      </Items>
    </MenuItem>
  </MainMenu>

  <MyObjects>
    <MyObject Name="VarPanel" Type="Panel" Assembly="BaseControls">
      <Visible>False</Visible>

      <MyObject Name="NumberOfOrdersVariable" Type="Variable" Assembly="SimpleControls">
        <Value>
          <Switch>
            <Case>
              <When>
                <Condition Name="NumberOfOrdersEqual0Condition" />
              </When>
              <Then>0</Then>
            </Case>
            <Case>
              <DataConnection SourceDataConnection="OrderPrimaryGetDataConnection">
                <Fields>
                  <Field Name="Count" />
                </Fields>
              </DataConnection>
            </Case>
          </Switch>
        </Value>
      </MyObject>

      <MyObject Name="CurrentPageVariable" Type="Variable" Assembly="SimpleControls">
        <Value>1</Value>
      </MyObject>

      <MyObject Name="TotalPagesVariable" Type="Variable" Assembly="SimpleControls" ChangeForm="False">
        <Value>
          <Switch>
            <Case>
              <When>
                <Condition Name="ItemsPerPageComboBoxIsNullCondition" />
              </When>
              <Then>1</Then>
            </Case>
            <Case>
              <Calculate>
                <Expression>Ceiling({0}/{1})</Expression>
                <Items>
                  <Item>
                    <Object Name="NumberOfOrdersVariable" />
                  </Item>
                  <Item>
                    <Object Name="ItemsPerPageComboBox" />
                  </Item>
                </Items>
              </Calculate>
            </Case>
          </Switch>
        </Value>
      </MyObject>

    </MyObject>

    <MyObject Name="HeadPanel" Type="Panel" Assembly="BaseControls">
      <Top>24</Top>
      <Left>0</Left>
      <Height>50</Height>
      <Width>
        <Form>
          <Property Name="Width" />
        </Form>
      </Width>
      <BackColor>HeadBackgroundColor</BackColor>

      <MyObject Name="HeadLabel" Type="Label" Assembly="BaseControls" ChangeForm="False">
        <Top>0</Top>
        <Left>10</Left>
        <Height>
          <Object Name="HeadPanel">
            <Property Name="Height" />
          </Object>
        </Height>
        <Width>
          <Calculate>
            <Expression>{0} - {1} - 10</Expression>
            <Items>
              <Item>
                <Object Name="HeadPanel">
                  <Property Name="Width" />
                </Object>
              </Item>
              <Item>
                <Object Name="HeadLabel">
                  <Property Name="Left" />
                </Object>
              </Item>
            </Items>
          </Calculate>
        </Width>
        <FontStyle>HeadFontStyle</FontStyle>
        <ForeColor>HeadForeColor</ForeColor>
        <TextAlign>MiddleLeft</TextAlign>
        <Text>
          <Parameter Name="Title" />
        </Text>
      </MyObject>
    </MyObject>

    <MyObject Name="ContentPanel" Type="Panel" Assembly="BaseControls">
      <Top>
        <Object Name="HeadPanel">
          <Property Name="Bottom" />
        </Object>
      </Top>
      <Left>0</Left>
      <Height>
        <Calculate>
          <Expression>{0} - {1}</Expression>
          <Items>
            <Item>
              <Form>
                <Property Name="Height" />
              </Form>
            </Item>
            <Item>
              <Object Name="ContentPanel">
                <Property Name="Top" />
              </Object>
            </Item>
          </Items>
        </Calculate>
      </Height>
      <Width>
        <Form>
          <Property Name="Width" />
        </Form>
      </Width>
      <TabIndex>1</TabIndex>
      <BackColor>ThemeBackgroundColor</BackColor>

      <MyObject Name="FilterPanel" Type="Panel" Assembly="BaseControls">
        <Top>0</Top>
        <Left>0</Left>
        <Height>
          <Object Name="ContentPanel">
            <Property Name="Height" />
          </Object>
        </Height>
        <Width>180</Width>
        <BackColor>ThemeBackgroundColor</BackColor>

        <MyObject Name="ActiveFilterVariable" Type="Variable" Assembly="SimpleControls" ChangeForm="False">
          <Value>Today</Value>
        </MyObject>

        <MyObject Name="TodayButton" Type="Button" Assembly="BaseControls">
          <Top>5</Top>
          <Left>10</Left>
          <Height>30</Height>
          <Width>
            <Calculate>
              <Expression>{0} - {1}*2</Expression>
              <Items>
                <Item>
                  <Object Name="FilterPanel">
                    <Property Name="Width" />
                  </Object>
                </Item>
                <Item>
                  <Object Name="TodayButton">
                    <Property Name="Left" />
                  </Object>
                </Item>
              </Items>
            </Calculate>
          </Width>
          <TextAlign>MiddleCenter</TextAlign>
          <FontStyle>ButtonFontStyle</FontStyle>
          <BackColor>
            <Switch>
              <Case>
                <When>
                  <Condition Name="FilterTodayIsActiveEqualCondition" />
                </When>
                <Then>ActiveFilterColor</Then>
              </Case>
              <Case>InactiveFilterColor</Case>
            </Switch>
          </BackColor>
          <FlatStyle>Flat</FlatStyle>
          <FlatBorderSize>1</FlatBorderSize>
          <FlatBorderColor>
            <Switch>
              <Case>
                <When>
                  <Condition Name="FilterTodayIsActiveEqualCondition" />
                </When>
                <Then>ActiveFilterColor</Then>
              </Case>
              <Case>ButtonFlatBorderColor</Case>
            </Switch>
          </FlatBorderColor>
          <FlatMouseDownBackColor>ButtonFlatMouseDownBackColor</FlatMouseDownBackColor>
          <FlatMouseOverBackColor>ButtonFlatMouseOverBackColor</FlatMouseOverBackColor>
          <Text>Сегодня</Text>
          <Commands>
            <Command Name="ActiveFilterValueSetCommand">Today</Command>
            <Command Name="OrderDataConnectionRefreshCommand" />
          </Commands>
        </MyObject>

        <MyObject Name="CurrentWeekButton" Type="Button" Assembly="BaseControls">
          <Top>
            <Calculate>
              <Expression>{0} + 5</Expression>
              <Items>
                <Item>
                  <Object Name="TodayButton">
                    <Property Name="Bottom" />
                  </Object>
                </Item>
              </Items>
            </Calculate>
          </Top>
          <Left>
            <Object Name="TodayButton">
              <Property Name="Left" />
            </Object>
          </Left>
          <Height>
            <Object Name="TodayButton">
              <Property Name="Height" />
            </Object>
          </Height>
          <Width>
            <Object Name="TodayButton">
              <Property Name="Width" />
            </Object>
          </Width>
          <TextAlign>MiddleCenter</TextAlign>
          <FontStyle>ButtonFontStyle</FontStyle>
          <BackColor>
            <Switch>
              <Case>
                <When>
                  <Condition Name="FilterCurrentWeekIsActiveEqualCondition" />
                </When>
                <Then>ActiveFilterColor</Then>
              </Case>
              <Case>InactiveFilterColor</Case>
            </Switch>
          </BackColor>
          <FlatStyle>Flat</FlatStyle>
          <FlatBorderSize>1</FlatBorderSize>
          <FlatBorderColor>
            <Switch>
              <Case>
                <When>
                  <Condition Name="FilterCurrentWeekIsActiveEqualCondition" />
                </When>
                <Then>ActiveFilterColor</Then>
              </Case>
              <Case>ButtonFlatBorderColor</Case>
            </Switch>
          </FlatBorderColor>
          <FlatMouseDownBackColor>ButtonFlatMouseDownBackColor</FlatMouseDownBackColor>
          <FlatMouseOverBackColor>ButtonFlatMouseOverBackColor</FlatMouseOverBackColor>
          <Text>Текущая неделя</Text>
          <Commands>
            <Command Name="ActiveFilterValueSetCommand">CurrentWeek</Command>
            <Command Name="OrderDataConnectionRefreshCommand" />
          </Commands>
        </MyObject>

        <MyObject Name="FortnightButton" Type="Button" Assembly="BaseControls">
          <Top>
            <Calculate>
              <Expression>{0} + 5</Expression>
              <Items>
                <Item>
                  <Object Name="CurrentWeekButton">
                    <Property Name="Bottom" />
                  </Object>
                </Item>
              </Items>
            </Calculate>
          </Top>
          <Left>
            <Object Name="TodayButton">
              <Property Name="Left" />
            </Object>
          </Left>
          <Height>
            <Object Name="TodayButton">
              <Property Name="Height" />
            </Object>
          </Height>
          <Width>
            <Object Name="TodayButton">
              <Property Name="Width" />
            </Object>
          </Width>
          <TextAlign>MiddleCenter</TextAlign>
          <FontStyle>ButtonFontStyle</FontStyle>
          <BackColor>
            <Switch>
              <Case>
                <When>
                  <Condition Name="FilterFortnightIsActiveEqualCondition" />
                </When>
                <Then>ActiveFilterColor</Then>
              </Case>
              <Case>InactiveFilterColor</Case>
            </Switch>
          </BackColor>
          <FlatStyle>Flat</FlatStyle>
          <FlatBorderSize>1</FlatBorderSize>
          <FlatBorderColor>
            <Switch>
              <Case>
                <When>
                  <Condition Name="FilterFortnightIsActiveEqualCondition" />
                </When>
                <Then>ActiveFilterColor</Then>
              </Case>
              <Case>ButtonFlatBorderColor</Case>
            </Switch>
          </FlatBorderColor>
          <FlatMouseDownBackColor>ButtonFlatMouseDownBackColor</FlatMouseDownBackColor>
          <FlatMouseOverBackColor>ButtonFlatMouseOverBackColor</FlatMouseOverBackColor>
          <Text>Две недели</Text>
          <Commands>
            <Command Name="ActiveFilterValueSetCommand">Fortnight</Command>
            <Command Name="OrderDataConnectionRefreshCommand" />
          </Commands>
        </MyObject>

        <MyObject Name="PeriodButton" Type="Button" Assembly="BaseControls">
          <Top>
            <Calculate>
              <Expression>{0} + 5</Expression>
              <Items>
                <Item>
                  <Object Name="FortnightButton">
                    <Property Name="Bottom" />
                  </Object>
                </Item>
              </Items>
            </Calculate>
          </Top>
          <Left>
            <Object Name="TodayButton">
              <Property Name="Left" />
            </Object>
          </Left>
          <Height>
            <Object Name="TodayButton">
              <Property Name="Height" />
            </Object>
          </Height>
          <Width>
            <Object Name="TodayButton">
              <Property Name="Width" />
            </Object>
          </Width>
          <TextAlign>MiddleCenter</TextAlign>
          <FontStyle>ButtonFontStyle</FontStyle>
          <BackColor>
            <Switch>
              <Case>
                <When>
                  <Condition Name="FilterPeriodIsActiveEqualCondition" />
                </When>
                <Then>ActiveFilterColor</Then>
              </Case>
              <Case>InactiveFilterColor</Case>
            </Switch>
          </BackColor>
          <FlatStyle>Flat</FlatStyle>
          <FlatBorderSize>1</FlatBorderSize>
          <FlatBorderColor>
            <Switch>
              <Case>
                <When>
                  <Condition Name="FilterPeriodIsActiveEqualCondition" />
                </When>
                <Then>ActiveFilterColor</Then>
              </Case>
              <Case>ButtonFlatBorderColor</Case>
            </Switch>
          </FlatBorderColor>
          <FlatMouseDownBackColor>ButtonFlatMouseDownBackColor</FlatMouseDownBackColor>
          <FlatMouseOverBackColor>ButtonFlatMouseOverBackColor</FlatMouseOverBackColor>
          <Text>Период</Text>
          <Commands>
            <Command Name="ActiveFilterValueSetCommand">Period</Command>
          </Commands>
        </MyObject>

        <MyObject Name="StartDateLabel" Type="Label" Assembly="BaseControls">
          <Top>
            <Calculate>
              <Expression>{0} + 10</Expression>
              <Items>
                <Item>
                  <Object Name="PeriodButton">
                    <Property Name="Bottom" />
                  </Object>
                </Item>
              </Items>
            </Calculate>
          </Top>
          <Left>
            <Object Name="TodayButton">
              <Property Name="Left" />
            </Object>
          </Left>
          <Width>
            <Calculate>
              <Expression>{0} - {1}*2</Expression>
              <Items>
                <Item>
                  <Object Name="FilterPanel">
                    <Property Name="Width" />
                  </Object>
                </Item>
                <Item>
                  <Object Name="StartDateLabel">
                    <Property Name="Left" />
                  </Object>
                </Item>
              </Items>
            </Calculate>
          </Width>
          <Height>20</Height>
          <TextAlign>MiddleLeft</TextAlign>
          <FontStyle>LabelFontStyle</FontStyle>
          <ForeColor>LabelForeColor</ForeColor>
          <Text>Дата начала</Text>
          <Visible>
            <Condition Name="FilterPeriodIsActiveEqualCondition" />
          </Visible>
        </MyObject>

        <MyObject Name="StartDateDateTimePicker" Type="DateTimePicker" Assembly="BaseControls" ChangeForm="False">
          <Top>
            <Object Name="StartDateLabel">
              <Property Name="Bottom" />
            </Object>
          </Top>
          <Left>
            <Object Name="StartDateLabel">
              <Property Name="Left" />
            </Object>
          </Left>
          <Width>
            <Object Name="StartDateLabel">
              <Property Name="Width" />
            </Object>
          </Width>
          <ShowCalendar>True</ShowCalendar>
          <NullValue Show="False" />
          <Value>
            <DateTime Variable="FirstDayOfCurrMonth" />
          </Value>
          <Visible>
            <Condition Name="FilterPeriodIsActiveEqualCondition" />
          </Visible>
        </MyObject>

        <MyObject Name="EndDateLabel" Type="Label" Assembly="BaseControls">
          <Top>
            <Calculate>
              <Expression>{0} + 5</Expression>
              <Items>
                <Item>
                  <Object Name="StartDateDateTimePicker">
                    <Property Name="Bottom" />
                  </Object>
                </Item>
              </Items>
            </Calculate>
          </Top>
          <Left>
            <Object Name="StartDateLabel">
              <Property Name="Left" />
            </Object>
          </Left>
          <Width>
            <Object Name="StartDateLabel">
              <Property Name="Width" />
            </Object>
          </Width>
          <Height>20</Height>
          <TextAlign>MiddleLeft</TextAlign>
          <FontStyle>LabelFontStyle</FontStyle>
          <ForeColor>LabelForeColor</ForeColor>
          <Text>Дата окончания</Text>
          <Visible>
            <Condition Name="FilterPeriodIsActiveEqualCondition" />
          </Visible>
        </MyObject>

        <MyObject Name="EndDateDateTimePicker" Type="DateTimePicker" Assembly="BaseControls" ChangeForm="False">
          <Top>
            <Object Name="EndDateLabel">
              <Property Name="Bottom" />
            </Object>
          </Top>
          <Left>
            <Object Name="StartDateLabel">
              <Property Name="Left" />
            </Object>
          </Left>
          <Width>
            <Object Name="StartDateLabel">
              <Property Name="Width" />
            </Object>
          </Width>
          <ShowCalendar>True</ShowCalendar>
          <NullValue Show="False" />
          <Value>
            <DateTime Variable="LastDayOfCurrMonth" />
          </Value>
          <Visible>
            <Condition Name="FilterPeriodIsActiveEqualCondition" />
          </Visible>
        </MyObject>

        <MyObject Name="ApplyButton" Type="Button" Assembly="BaseControls">
          <Top>
            <Calculate>
              <Expression>{0} + 5</Expression>
              <Items>
                <Item>
                  <Object Name="EndDateDateTimePicker">
                    <Property Name="Bottom" />
                  </Object>
                </Item>
              </Items>
            </Calculate>
          </Top>
          <Left>
            <Object Name="TodayButton">
              <Property Name="Left" />
            </Object>
          </Left>
          <Width>
            <Object Name="StartDateLabel">
              <Property Name="Width" />
            </Object>
          </Width>
          <Height>30</Height>
          <TextAlign>MiddleCenter</TextAlign>
          <FontStyle>ButtonFontStyle</FontStyle>
          <ImageAlign>MiddleLeft</ImageAlign>
          <FlatStyle>Flat</FlatStyle>
          <FlatBorderSize>1</FlatBorderSize>
          <FlatBorderColor>ButtonFlatBorderColor</FlatBorderColor>
          <FlatMouseDownBackColor>ButtonFlatMouseDownBackColor</FlatMouseDownBackColor>
          <FlatMouseOverBackColor>ButtonFlatMouseOverBackColor</FlatMouseOverBackColor>
          <Text>Применить</Text>
          <Commands>
            <Command Name="OrderDataConnectionRefreshCommand" />
          </Commands>
          <Visible>
            <Condition Name="FilterPeriodIsActiveEqualCondition" />
          </Visible>
        </MyObject>
      </MyObject>

      <MyObject Name="FilterSeparatePanel" Type="Panel" Assembly="BaseControls">
        <Top>5</Top>
        <Left>
          <Object Name="FilterPanel">
            <Property Name="Right" />
          </Object>
        </Left>
        <Height>
          <Calculate>
            <Expression>{0} - 10</Expression>
            <Items>
              <Item>
                <Object Name="ContentPanel">
                  <Property Name="Height" />
                </Object>
              </Item>
            </Items>
          </Calculate>
        </Height>
        <Width>1</Width>
        <BackColor>ThemeSeparateBackgroundColor</BackColor>
      </MyObject>

      <MyObject Name="DataPanel" Type="Panel" Assembly="BaseControls">
        <Top>0</Top>
        <Left>
          <Object Name="FilterSeparatePanel">
            <Property Name="Right" />
          </Object>
        </Left>
        <Height>
          <Object Name="FilterPanel">
            <Property Name="Height" />
          </Object>
        </Height>
        <Width>
          <Calculate>
            <Expression>{0} - {1}</Expression>
            <Items>
              <Item>
                <Object Name="ContentPanel">
                  <Property Name="Width" />
                </Object>
              </Item>
              <Item>
                <Object Name="DataPanel">
                  <Property Name="Left" />
                </Object>
              </Item>
            </Items>
          </Calculate>
        </Width>
        <BackColor>ThemeBackgroundColor</BackColor>

        <MyObject Name="OrderDatabaseTable" Type="DatabaseTable" Assembly="ComplexControls">
          <Top>5</Top>
          <Left>10</Left>
          <Height>
            <Calculate>
              <Expression>{0} - {1}*2 - 5 - {2}</Expression>
              <Items>
                <Item>
                  <Object Name="DataPanel">
                    <Property Name="Height" />
                  </Object>
                </Item>
                <Item>
                  <Object Name="OrderDatabaseTable">
                    <Property Name="Top" />
                  </Object>
                </Item>
                <Item>
                  <Object Name="PagePanel">
                    <Property Name="Height" />
                  </Object>
                </Item>
              </Items>
            </Calculate>
          </Height>
          <Width>
            <Calculate>
              <Expression>{0} - {1}*2 - {2} - 5</Expression>
              <Items>
                <Item>
                  <Object Name="DataPanel">
                    <Property Name="Width" />
                  </Object>
                </Item>
                <Item>
                  <Object Name="OrderDatabaseTable">
                    <Property Name="Left" />
                  </Object>
                </Item>
                <Item>
                  <Object Name="OrderAddButton">
                    <Property Name="Width" />
                  </Object>
                </Item>
              </Items>
            </Calculate>
          </Width>
          <AllowResizeColumns Value="False" />
          <AllowResizeRows Value="False" />
          <AllowInsert>False</AllowInsert>
          <AllowUpdate>False</AllowUpdate>
          <AllowDelete>False</AllowDelete>
          <AutoSizeColumnsMode Value="Disable" />
          <TabIndex>2</TabIndex>
          <SourceDataConnection Name="OrderPrimaryGetDataConnection" />
          <Columns>
            <Column Name="OrderId" Type="DatabaseTableColumnTextBox" Assembly="DatabaseTableColumnControls">
              <Visible>False</Visible>
            </Column>
            <Column Name="ClientId" Type="DatabaseTableColumnTextBox" Assembly="DatabaseTableColumnControls">
              <Visible>False</Visible>
            </Column>
            <Column Name="CityId" Type="DatabaseTableColumnTextBox" Assembly="DatabaseTableColumnControls">
              <Visible>False</Visible>
            </Column>
            <Column Name="RowNumber" Type="DatabaseTableColumnTextBox" Assembly="DatabaseTableColumnControls">
              <Title>№</Title>
              <Width>40</Width>
              <AutoFill Type="RowNumber" />
              <Alignment Value="MiddleCenter" />
              <AutoSizeMode Value="None" />
            </Column>
            <Column Name="OrderNumber" Type="DatabaseTableColumnTextBox" Assembly="DatabaseTableColumnControls">
              <Title>Номер заказа</Title>
              <Width>90</Width>
              <AutoSizeMode Value="None" />
              <Alignment Value="MiddleCenter" />
            </Column>
            <Column Name="OrderDate" Type="DatabaseTableColumnTextBox" Assembly="DatabaseTableColumnControls">
              <Title>Дата и время заказа</Title>
              <Width>130</Width>
              <AutoSizeMode Value="None" />
              <Alignment Value="MiddleCenter" />
              <DataType Type="DateTimeDataType" Format="dd.MM.yyyy HH:mm" />
            </Column>
            <Column Name="CityTitle" Type="DatabaseTableColumnTextBox" Assembly="DatabaseTableColumnControls">
              <Title>Город</Title>
              <Width>150</Width>
              <AutoSizeMode Value="None" />
              <Substitution SourceColumn="CityId">
                <DataConnection SourceDataConnection="CityPrimaryGetDataConnection">
                  <Fields>
                    <Field Name="CityId" />
                    <Field Name="Title" />
                  </Fields>
                </DataConnection>
              </Substitution>
            </Column>
            <Column Name="ClientTitle" Type="DatabaseTableColumnTextBox" Assembly="DatabaseTableColumnControls">
              <Title>Клиент</Title>
              <Width>300</Width>
              <AutoSizeMode Value="Fill" />
              <Substitution SourceColumn="ClientId">
                <DataConnection SourceDataConnection="ClientPrimaryGetDataConnection">
                  <Fields>
                    <Field Name="ClientId" />
                    <Field Name="Title" />
                  </Fields>
                </DataConnection>
              </Substitution>
            </Column>
          </Columns>
        </MyObject>

        <MyObject Name="OrderAddButton" Type="Button" Assembly="BaseControls">
          <Top>
            <Object Name="OrderDatabaseTable">
              <Property Name="Top" />
            </Object>
          </Top>
          <Left>
            <Calculate>
              <Expression>{0} + 5</Expression>
              <Items>
                <Item>
                  <Object Name="OrderDatabaseTable">
                    <Property Name="Right" />
                  </Object>
                </Item>
              </Items>
            </Calculate>
          </Left>
          <Width>40</Width>
          <Height>40</Height>
          <TabIndex>3</TabIndex>
          <Hint>Добавить запись</Hint>
          <BackgroundImage>Images\24x24\plus.png</BackgroundImage>
          <BackgroundImageLayout>Center</BackgroundImageLayout>
          <FlatStyle>Flat</FlatStyle>
          <FlatBorderSize>1</FlatBorderSize>
          <FlatBorderColor>ButtonFlatBorderColor</FlatBorderColor>
          <FlatMouseDownBackColor>ButtonFlatMouseDownBackColor</FlatMouseDownBackColor>
          <FlatMouseOverBackColor>ButtonFlatMouseOverBackColor</FlatMouseOverBackColor>
          <Commands>
            <Command Name="EmptyOrderInsertSaveCommand" />
            <Command Name="OrderAddFormShowCommand" />
          </Commands>
        </MyObject>

        <MyObject Name="OrderEditButton" Type="Button" Assembly="BaseControls">
          <Top>
            <Calculate>
              <Expression>{0} + 5</Expression>
              <Items>
                <Item>
                  <Object Name="OrderAddButton">
                    <Property Name="Bottom" />
                  </Object>
                </Item>
              </Items>
            </Calculate>
          </Top>
          <Left>
            <Object Name="OrderAddButton">
              <Property Name="Left" />
            </Object>
          </Left>
          <Width>
            <Object Name="OrderAddButton">
              <Property Name="Width" />
            </Object>
          </Width>
          <Height>
            <Object Name="OrderAddButton">
              <Property Name="Height" />
            </Object>
          </Height>
          <TabIndex>4</TabIndex>
          <Hint>Редактировать запись...</Hint>
          <BackgroundImage>Images\24x24\pencil.png</BackgroundImage>
          <BackgroundImageLayout>Center</BackgroundImageLayout>
          <FlatStyle>Flat</FlatStyle>
          <FlatBorderSize>1</FlatBorderSize>
          <FlatBorderColor>ButtonFlatBorderColor</FlatBorderColor>
          <FlatMouseDownBackColor>ButtonFlatMouseDownBackColor</FlatMouseDownBackColor>
          <FlatMouseOverBackColor>ButtonFlatMouseOverBackColor</FlatMouseOverBackColor>
          <Enabled>
            <Condition Name="OrderSelectedCondition" />
          </Enabled>
          <Commands>
            <Command Name="OrderEditFormShowCommand" />
          </Commands>
          <DisabledMode>True</DisabledMode>
          <DisabledText>Выберите запись для редактирования.</DisabledText>
        </MyObject>

        <MyObject Name="OrderDeleteButton" Type="Button" Assembly="BaseControls">
          <Top>
            <Calculate>
              <Expression>{0} + 5</Expression>
              <Items>
                <Item>
                  <Object Name="OrderEditButton">
                    <Property Name="Bottom" />
                  </Object>
                </Item>
              </Items>
            </Calculate>
          </Top>
          <Left>
            <Object Name="OrderAddButton">
              <Property Name="Left" />
            </Object>
          </Left>
          <Width>
            <Object Name="OrderAddButton">
              <Property Name="Width" />
            </Object>
          </Width>
          <Height>
            <Object Name="OrderAddButton">
              <Property Name="Height" />
            </Object>
          </Height>
          <TabIndex>5</TabIndex>
          <Hint>Удалить запись</Hint>
          <BackgroundImage>Images\24x24\delete.png</BackgroundImage>
          <BackgroundImageLayout>Center</BackgroundImageLayout>
          <FlatStyle>Flat</FlatStyle>
          <FlatBorderSize>1</FlatBorderSize>
          <FlatBorderColor>ButtonFlatBorderColor</FlatBorderColor>
          <FlatMouseDownBackColor>ButtonFlatMouseDownBackColor</FlatMouseDownBackColor>
          <FlatMouseOverBackColor>ButtonFlatMouseOverBackColor</FlatMouseOverBackColor>
          <Enabled>
            <Condition Name="OrderSelectedCondition" />
          </Enabled>
          <Commands>
            <Command Name="OrderDeleteMessageBoxCommand" />
          </Commands>
          <DisabledMode>True</DisabledMode>
          <DisabledText>Выберите запись для удаления.</DisabledText>
        </MyObject>


        <MyObject Name="PagePanel" Type="Panel" Assembly="BaseControls">
          <Top>
            <Object Name="OrderDatabaseTable">
              <Property Name="Bottom" />
            </Object>
          </Top>
          <Left>
            <Calculate>
              <Expression>Ceiling(({0} - {1})/2)</Expression>
              <Items>
                <Item>
                  <Object Name="ContentPanel">
                    <Property Name="Width" />
                  </Object>
                </Item>
                <Item>
                  <Object Name="PagePanel">
                    <Property Name="Width" />
                  </Object>
                </Item>
              </Items>
            </Calculate>
          </Left>
          <Height>30</Height>
          <Width>
            <Object Name="TotalItemsLabel">
              <Property Name="Right" />
            </Object>
          </Width>

          <MyObject Name="FirstPageButton" Type="Button" Assembly="BaseControls">
            <Top>5</Top>
            <Left>0</Left>
            <Height>
              <Object Name="CurrentPageTextBox">
                <Property Name="Height" />
              </Object>
            </Height>
            <Width>
              <Object Name="FirstPageButton">
                <Property Name="Height" />
              </Object>
            </Width>
            <FlatStyle>Flat</FlatStyle>
            <FlatBorderSize>0</FlatBorderSize>
            <FlatBorderColor>ButtonFlatBorderColor</FlatBorderColor>
            <FlatMouseDownBackColor>ButtonFlatMouseDownBackColor</FlatMouseDownBackColor>
            <FlatMouseOverBackColor>ButtonFlatMouseOverBackColor</FlatMouseOverBackColor>
            <BackgroundImageLayout>Center</BackgroundImageLayout>
            <BackgroundImage>Images\16x16\arrow-collapse-left.png</BackgroundImage>
            <Commands>
              <Command Name="CurrentPageVariableValueSetCommand">1</Command>
            </Commands>
            <Enabled>
              <And>
                <Not>
                  <Condition Name="CurrentPageVariableEqual1Condition" />
                </Not>
                <Not>
                  <Condition Name="NumberOfOrdersVariableEqual0Condition" />
                </Not>
              </And>
            </Enabled>
          </MyObject>

          <MyObject Name="PrevPageButton" Type="Button" Assembly="BaseControls">
            <Top>
              <Object Name="FirstPageButton">
                <Property Name="Top" />
              </Object>
            </Top>
            <Left>
              <Calculate>
                <Expression>{0} + 3</Expression>
                <Items>
                  <Item>
                    <Object Name="FirstPageButton">
                      <Property Name="Right" />
                    </Object>
                  </Item>
                </Items>
              </Calculate>
            </Left>
            <Height>
              <Object Name="FirstPageButton">
                <Property Name="Height" />
              </Object>
            </Height>
            <Width>
              <Object Name="FirstPageButton">
                <Property Name="Width" />
              </Object>
            </Width>
            <FlatStyle>Flat</FlatStyle>
            <FlatBorderSize>0</FlatBorderSize>
            <FlatBorderColor>ButtonFlatBorderColor</FlatBorderColor>
            <FlatMouseDownBackColor>ButtonFlatMouseDownBackColor</FlatMouseDownBackColor>
            <FlatMouseOverBackColor>ButtonFlatMouseOverBackColor</FlatMouseOverBackColor>
            <BackgroundImageLayout>Center</BackgroundImageLayout>
            <BackgroundImage>Images\16x16\arrow-left.png</BackgroundImage>
            <Commands>
              <Command Name="CurrentPageVariableDecValueSetCommand" />
            </Commands>
            <Enabled>
              <And>
                <Not>
                  <Condition Name="CurrentPageVariableEqual1Condition" />
                </Not>
                <Not>
                  <Condition Name="NumberOfOrdersVariableEqual0Condition" />
                </Not>
              </And>
            </Enabled>
          </MyObject>

          <MyObject Name="CurrentPageTextBox" Type="TextBox" Assembly="BaseControls" ChangeForm="False">
            <Top>
              <Object Name="PrevPageButton">
                <Property Name="Top" />
              </Object>
            </Top>
            <Left>
              <Calculate>
                <Expression>{0} + 3</Expression>
                <Items>
                  <Item>
                    <Object Name="PrevPageButton">
                      <Property Name="Right" />
                    </Object>
                  </Item>
                </Items>
              </Calculate>
            </Left>
            <Width>30</Width>
            <MaxLength>3</MaxLength>
            <AllowedSymbols>0123456789</AllowedSymbols>
            <TextAlign>Right</TextAlign>
            <Text>
              <Object Name="CurrentPageVariable" />
            </Text>
          </MyObject>

          <MyObject Name="TotalPagesLabel" Type="Label" Assembly="BaseControls" ChangeForm="False">
            <Top>
              <Object Name="PrevPageButton">
                <Property Name="Top" />
              </Object>
            </Top>
            <Left>
              <Object Name="CurrentPageTextBox">
                <Property Name="Right" />
              </Object>
            </Left>
            <Height>20</Height>
            <Width>40</Width>
            <TextAlign>MiddleLeft</TextAlign>
            <Text>
              <String>
                <Format>/ {0}</Format>
                <Items>
                  <Item>
                    <Switch>
                      <Case>
                        <When>
                          <Condition Name="NumberOfOrdersVariableEqual0Condition" />
                        </When>
                        <Then>1</Then>
                      </Case>
                      <Case>
                        <Object Name="TotalPagesVariable" />
                      </Case>
                    </Switch>
                  </Item>
                </Items>
              </String>
            </Text>
          </MyObject>

          <MyObject Name="NextPageButton" Type="Button" Assembly="BaseControls">
            <Top>
              <Object Name="FirstPageButton">
                <Property Name="Top" />
              </Object>
            </Top>
            <Left>
              <Calculate>
                <Expression>{0} + 3</Expression>
                <Items>
                  <Item>
                    <Object Name="TotalPagesLabel">
                      <Property Name="Right" />
                    </Object>
                  </Item>
                </Items>
              </Calculate>
            </Left>
            <Height>
              <Object Name="FirstPageButton">
                <Property Name="Height" />
              </Object>
            </Height>
            <Width>
              <Object Name="FirstPageButton">
                <Property Name="Width" />
              </Object>
            </Width>
            <FlatStyle>Flat</FlatStyle>
            <FlatBorderSize>0</FlatBorderSize>
            <FlatBorderColor>ButtonFlatBorderColor</FlatBorderColor>
            <FlatMouseDownBackColor>ButtonFlatMouseDownBackColor</FlatMouseDownBackColor>
            <FlatMouseOverBackColor>ButtonFlatMouseOverBackColor</FlatMouseOverBackColor>
            <BackgroundImageLayout>Center</BackgroundImageLayout>
            <BackgroundImage>Images\16x16\arrow-right.png</BackgroundImage>
            <Commands>
              <Command Name="CurrentPageVariableIncValueSetCommand" />
            </Commands>
            <Enabled>
              <And>
                <Not>
                  <Condition Name="CurrentPageVariableEqualMaxCondition" />
                </Not>
                <Not>
                  <Condition Name="NumberOfOrdersVariableEqual0Condition" />
                </Not>
              </And>
            </Enabled>
          </MyObject>

          <MyObject Name="LastPageButton" Type="Button" Assembly="BaseControls">
            <Top>
              <Object Name="PrevPageButton">
                <Property Name="Top" />
              </Object>
            </Top>
            <Left>
              <Calculate>
                <Expression>{0} + 3</Expression>
                <Items>
                  <Item>
                    <Object Name="NextPageButton">
                      <Property Name="Right" />
                    </Object>
                  </Item>
                </Items>
              </Calculate>
            </Left>
            <Height>
              <Object Name="FirstPageButton">
                <Property Name="Height" />
              </Object>
            </Height>
            <Width>
              <Object Name="FirstPageButton">
                <Property Name="Width" />
              </Object>
            </Width>
            <FlatStyle>Flat</FlatStyle>
            <FlatBorderSize>0</FlatBorderSize>
            <FlatBorderColor>ButtonFlatBorderColor</FlatBorderColor>
            <FlatMouseDownBackColor>ButtonFlatMouseDownBackColor</FlatMouseDownBackColor>
            <FlatMouseOverBackColor>ButtonFlatMouseOverBackColor</FlatMouseOverBackColor>
            <BackgroundImageLayout>Center</BackgroundImageLayout>
            <BackgroundImage>Images\16x16\arrow-collapse-right.png</BackgroundImage>
            <Commands>
              <Command Name="CurrentPageVariableValueSetCommand">
                <Object Name="TotalPagesVariable" />
              </Command>
            </Commands>
            <Enabled>
              <And>
                <Not>
                  <Condition Name="CurrentPageVariableEqualMaxCondition" />
                </Not>
                <Not>
                  <Condition Name="NumberOfOrdersVariableEqual0Condition" />
                </Not>
              </And>
            </Enabled>
          </MyObject>
          <MyObject Name="PerPageLabel" Type="Label" Assembly="BaseControls">
            <Top>
              <Object Name="PrevPageButton">
                <Property Name="Top" />
              </Object>
            </Top>
            <Left>
              <Calculate>
                <Expression>{0} + 20</Expression>
                <Items>
                  <Item>
                    <Object Name="LastPageButton">
                      <Property Name="Right" />
                    </Object>
                  </Item>
                </Items>
              </Calculate>
            </Left>
            <Height>20</Height>
            <Width>110</Width>
            <TextAlign>MiddleRight</TextAlign>
            <Text>строк на странице</Text>
          </MyObject>

          <MyObject Name="ItemsPerPageComboBox" Type="ComboBox" Assembly="BaseControls" ChangeForm="False">
            <Top>
              <Object Name="PrevPageButton">
                <Property Name="Top" />
              </Object>
            </Top>
            <Left>
              <Object Name="PerPageLabel">
                <Property Name="Right" />
              </Object>
            </Left>
            <Width>50</Width>
            <ValueList>
              <Structure Type="Table">
                <Row>
                  <Item />
                  <Item>[Все]</Item>
                </Row>
                <Row>
                  <Item>5</Item>
                  <Item>5</Item>
                </Row>
                <Row>
                  <Item>10</Item>
                  <Item>10</Item>
                </Row>
                <Row>
                  <Item>50</Item>
                  <Item>50</Item>
                </Row>
                <Row>
                  <Item>100</Item>
                  <Item>100</Item>
                </Row>
              </Structure>
            </ValueList>
            <Value>50</Value>
          </MyObject>

          <MyObject Name="TotalItemsLabel" Type="Label" Assembly="BaseControls" ChangeForm="False">
            <Top>
              <Object Name="PrevPageButton">
                <Property Name="Top" />
              </Object>
            </Top>
            <Left>
              <Calculate>
                <Expression>{0} + 3</Expression>
                <Items>
                  <Item>
                    <Object Name="ItemsPerPageComboBox">
                      <Property Name="Right" />
                    </Object>
                  </Item>
                </Items>
              </Calculate>
            </Left>
            <Height>20</Height>
            <Width>60</Width>
            <TextAlign>MiddleLeft</TextAlign>
            <Text>
              <String>
                <Format>из {0}</Format>
                <Items>
                  <Item>
                    <Switch>
                      <Case>
                        <When>
                          <Condition Name="NumberOfOrdersVariableEqual0Condition" />
                        </When>
                        <Then>0</Then>
                      </Case>
                      <Case>
                        <Object Name="NumberOfOrdersVariable" />
                      </Case>
                    </Switch>
                  </Item>
                </Items>
              </String>
            </Text>
          </MyObject>

        </MyObject>
      </MyObject>
    </MyObject>
  </MyObjects>
</Form>